shamsi_datetime/__init__.py
shamsi_datetime/datetime.py
tests/__init__.py
tests/test_datetime.py
shamsi_datetime-0.2.0.dist-info/LICENSE
shamsi_datetime-0.2.0.dist-info/METADATA
shamsi_datetime-0.2.0.dist-info/WHEEL
shamsi_datetime-0.2.0.dist-info/top_level.txt
shamsi_datetime-0.2.0.dist-info/RECORD
