Metadata-Version: 2.1
Name: shamsi_datetime
Version: 0.2.0
Summary: A Shamsi (Jalali) datetime class for NumPy integration
Author: Ali Razmjooei
Author-email: your.email@example.com
License: MIT
Classifier: Programming Language :: Python :: 3
Classifier: License :: OSI Approved :: MIT License
Classifier: Operating System :: OS Independent
Requires-Python: >=3.6
License-File: LICENSE
Requires-Dist: numpy
Requires-Dist: jdatetime
